SynologyAPI/__init__.py
SynologyAPI/__main__.py
SynologyAPI/synology_API.py
SynologyAPI_NPP-1.7.5.dist-info/LICENSE
SynologyAPI_NPP-1.7.5.dist-info/METADATA
SynologyAPI_NPP-1.7.5.dist-info/WHEEL
SynologyAPI_NPP-1.7.5.dist-info/entry_points.txt
SynologyAPI_NPP-1.7.5.dist-info/top_level.txt
SynologyAPI_NPP-1.7.5.dist-info/RECORD
