Metadata-Version: 2.1
Name: SynologyAPI-NPP
Version: 1.7.5
Summary: API Basica per a synologys Active Backup For Buissiness
Home-page: https://github.com/NilPujolPorta/Synology_API-NPP
Author: Nil Pujol Porta
Author-email: nilpujolporta@gmail.com
License: GNU
Platform: UNKNOWN
License-File: LICENSE
Requires-Dist: argparse
Requires-Dist: setuptools (>=42)
Requires-Dist: wheel
Requires-Dist: openpyxl
Requires-Dist: pyyaml
Requires-Dist: requests
Requires-Dist: mysql-connector-python
Requires-Dist: tqdm
